{"0031b98f": {"crc32": "0x0031b98f", "crc32_128kb": "0x0031b98f", "region": "NTSC-U", "release_name": "C-64 Import Test Diag (USA, Europe) (Program)", "title": "C-64 Import Test Diag (USA, Europe)"}, "0068933c": {"crc32": "0x0068933c", "crc32_128kb": "0xb70fe131", "region": "NTSC-U", "release_name": "Expert, The (USA, Europe) (Program) (Euc29)", "title": "Expert, The (USA, Europe) (Euc29)"}, "01562925": {"crc32": "0x01562925", "crc32_128kb": "0x01562925", "region": "NTSC-U", "release_name": "20 (World) (Aftermarket) (Unl)", "title": "20"}, "027cbe8c": {"crc32": "0x027cbe8c", "crc32_128kb": "0x9b5e39f5", "region": "NTSC-U", "release_name": "Galaga (World) (v1.05) (Aftermarket) (Unl)", "title": "Galaga (v1.05)"}, "0354b59c": {"crc32": "0x0354b59c", "crc32_128kb": "0x0354b59c", "region": "NTSC-U", "release_name": "Up for Grabs (USA, Europe)", "title": "Up for Grabs (USA, Europe)"}, "036788ed": {"crc32": "0x036788ed", "crc32_128kb": "0x036788ed", "region": "NTSC-U", "release_name": "Magic Desk I - Type and File (USA, Europe) (VICE) (Program)", "title": "Magic Desk I - Type and File (USA, Europe) (VICE)"}, "04010756": {"crc32": "0x04010756", "crc32_128kb": "0x04010756", "region": "NTSC-U", "release_name": "Utah Counties Tutorial (USA)", "title": "Utah Counties Tutorial"}, "042e05b4": {"crc32": "0x042e05b4", "crc32_128kb": "0x042e05b4", "region": "NTSC-U", "release_name": "Action Replay Professional (USA) (v5.0) (Program) (Unl)", "title": "Action Replay Professional (v5.0)"}, "04f400e2": {"crc32": "0x04f400e2", "crc32_128kb": "0x04f400e2", "region": "NTSC-J", "release_name": "Radar Rat Race (Japan) (v02) (MAX) (Alt)", "title": "Radar Rat Race (v02) (MAX)"}, "0640ecd2": {"crc32": "0x0640ecd2", "crc32_128kb": "0x0640ecd2", "region": "NTSC-U", "release_name": "PS-64 (Finland) (v2.00) (Program)", "title": "PS-64 (Finland) (v2.00)"}, "064eaa1f": {"crc32": "0x064eaa1f", "crc32_128kb": "0x064eaa1f", "region": "NTSC-U", "release_name": "Music Machine (USA, Europe) (MAX)", "title": "Music Machine (USA, Europe) (MAX)"}, "0695eafc": {"crc32": "0x0695eafc", "crc32_128kb": "0x0695eafc", "region": "NTSC-U", "release_name": "Pastfinder (USA, Europe)", "title": "Pastfinder (USA, Europe)"}, "077c86bd": {"crc32": "0x077c86bd", "crc32_128kb": "0xe2da1aa8", "region": "NTSC-U", "release_name": "Double Dragon (USA, Europe) (HES)", "title": "Double Dragon (USA, Europe) (HES)"}, "0988b37f": {"crc32": "0x0988b37f", "crc32_128kb": "0x0988b37f", "region": "NTSC-U", "release_name": "Speedsaver $C000 (USA, Europe) (Program)", "title": "Speedsaver $C000 (USA, Europe)"}, "0b2a7d46": {"crc32": "0x0b2a7d46", "crc32_128kb": "0x0b2a7d46", "region": "NTSC-U", "release_name": "Speedsaver Combi (USA, Europe) (Program)", "title": "Speedsaver Combi (USA, Europe)"}, "0b2f427e": {"crc32": "0x0b2f427e", "crc32_128kb": "0x0b2f427e", "region": "NTSC-U", "release_name": "Number Tumblers (USA, Europe)", "title": "Number Tumblers (USA, Europe)"}, "0b5eea1d": {"crc32": "0x0b5eea1d", "crc32_128kb": "0x0b5eea1d", "region": "NTSC-U", "release_name": "Stix (USA, Europe)", "title": "Stix (USA, Europe)"}, "0b6a0bef": {"crc32": "0x0b6a0bef", "crc32_128kb": "0x0b6a0bef", "region": "NTSC-U", "release_name": "Ernie's Magic Shapes (USA, Europe)", "title": "Ernie's Magic Shapes (USA, Europe)"}, "0c74ad83": {"crc32": "0x0c74ad83", "crc32_128kb": "0x0c74ad83", "region": "NTSC-U", "release_name": "Arnie Armchair's Howzat Cricket Game (USA, Europe)", "title": "Arnie Armchair's Howzat Cricket Game (USA, Europe)"}, "0c9a3da6": {"crc32": "0x0c9a3da6", "crc32_128kb": "0x926ab185", "region": "NTSC-U", "release_name": "Merge 64 (World) (Aftermarket) (Unl)", "title": "Merge 64"}, "0ca54785": {"crc32": "0x0ca54785", "crc32_128kb": "0x0ca54785", "region": "NTSC-U", "release_name": "Big Bird's Funhouse (USA, Europe)", "title": "Big Bird's Funhouse (USA, Europe)"}, "0d4e2f06": {"crc32": "0x0d4e2f06", "crc32_128kb": "0xc1833cde", "region": "NTSC-U", "release_name": "Lady Pac (World) (Aftermarket) (Unl)", "title": "Lady Pac"}, "0ecf0b4a": {"crc32": "0x0ecf0b4a", "crc32_128kb": "0x0ecf0b4a", "region": "NTSC-U", "release_name": "Gorf (USA, Europe)", "title": "Gorf (USA, Europe)"}, "0f61409b": {"crc32": "0x0f61409b", "crc32_128kb": "0x0f61409b", "region": "NTSC-U", "release_name": "Battlezone (USA, Europe)", "title": "Battlezone (USA, Europe)"}, "10192e17": {"crc32": "0x10192e17", "crc32_128kb": "0x10192e17", "region": "NTSC-U", "release_name": "Movie Musical Madness Starring the Jazz Scats (USA, Europe)", "title": "Movie Musical Madness Starring the Jazz Scats (USA, Europe)"}, "1040dcbe": {"crc32": "0x1040dcbe", "crc32_128kb": "0x1040dcbe", "region": "NTSC-U", "release_name": "Stat 64 (USA, Europe) (Program)", "title": "Stat 64 (USA, Europe)"}, "1045728a": {"crc32": "0x1045728a", "crc32_128kb": "0x1045728a", "region": "NTSC-U", "release_name": "Rootin' Tootin' (USA, Europe)", "title": "Rootin' Tootin' (USA, Europe)"}, "113c8dcb": {"crc32": "0x113c8dcb", "crc32_128kb": "0x6ddc578a", "region": "PAL", "release_name": "Chase H.Q. II - Special Criminal Investigation (Europe)", "title": "Chase H.Q. II - Special Criminal Investigation"}, "115a0d9a": {"crc32": "0x115a0d9a", "crc32_128kb": "0x115a0d9a", "region": "NTSC-U", "release_name": "Halftime Battlin' Bands (USA, Europe)", "title": "Halftime Battlin' Bands (USA, Europe)"}, "11b15910": {"crc32": "0x11b15910", "crc32_128kb": "0x11b15910", "region": "NTSC-U", "release_name": "Space Shuttle - A Journey into Space (USA, Europe)", "title": "Space Shuttle - A Journey into Space (USA, Europe)"}, "121c4a0a": {"crc32": "0x121c4a0a", "crc32_128kb": "0x121c4a0a", "region": "NTSC-U", "release_name": "Jack Attack (USA, Europe)", "title": "Jack Attack (USA, Europe)"}, "13d082c1": {"crc32": "0x13d082c1", "crc32_128kb": "0x1eca6f18", "region": "NTSC-U", "release_name": "Professional Skateboard Simulator + Fast Food + Pro Tennis Simulator (USA, Europe) (Fun Play)", "title": "Professional Skateboard Simulator + Fast Food + Pro Tennis Simulator (USA, Europe) (Fun Play)"}, "13d0f167": {"crc32": "0x13d0f167", "crc32_128kb": "0x13d0f167", "region": "NTSC-U", "release_name": "Merge 64 (World) (Aftermarket) (Unl)", "title": "Merge 64"}, "13e1e63b": {"crc32": "0x13e1e63b", "crc32_128kb": "0x13e1e63b", "region": "NTSC-U", "release_name": "Lode Runner (USA, Europe)", "title": "Lode Runner (USA, Europe)"}, "1469e917": {"crc32": "0x1469e917", "crc32_128kb": "0xeea86119", "region": "NTSC-U", "release_date": "1989", "release_name": "After the War (USA, Europe)", "title": "After the War (USA, Europe)"}, "167c05fb": {"crc32": "0x167c05fb", "crc32_128kb": "0x167c05fb", "region": "NTSC-U", "release_name": "Delta Drawing (USA, Europe) (Program)", "title": "Delta Drawing (USA, Europe)"}, "16a574f9": {"crc32": "0x16a574f9", "crc32_128kb": "0x16a574f9", "region": "NTSC-U", "release_name": "Zone Ranger (USA, Europe)", "title": "Zone Ranger (USA, Europe)"}, "16a681cb": {"crc32": "0x16a681cb", "crc32_128kb": "0x16a681cb", "region": "NTSC-U", "release_name": "Laser Cycles (USA, Europe)", "title": "Laser Cycles (USA, Europe)"}, "18051680": {"crc32": "0x18051680", "crc32_128kb": "0x18051680", "region": "NTSC-U", "release_name": "Pit, The (USA, Europe)", "title": "Pit, The (USA, Europe)"}, "185f2310": {"crc32": "0x185f2310", "crc32_128kb": "0x185f2310", "region": "NTSC-U", "release_name": "Alphabet Zoo (USA, Europe)", "title": "Alphabet Zoo (USA, Europe)"}, "1862e4bd": {"crc32": "0x1862e4bd", "crc32_128kb": "0x9e905167", "region": "NTSC-U", "release_name": "Cyberball (USA, Europe)", "title": "Cyberball (USA, Europe)"}, "1a47f824": {"crc32": "0x1a47f824", "crc32_128kb": "0x1a47f824", "region": "NTSC-U", "release_name": "Learning with Leeper (USA, Europe)", "title": "Learning with Leeper (USA, Europe)"}, "1a51e6ee": {"crc32": "0x1a51e6ee", "crc32_128kb": "0x1a51e6ee", "region": "NTSC-U", "release_name": "Cosmic Life (USA, Europe)", "title": "Cosmic Life (USA, Europe)"}, "1a5996da": {"crc32": "0x1a5996da", "crc32_128kb": "0x1a5996da", "region": "NTSC-U", "release_name": "Wizard of Wor (USA, Europe)", "title": "Wizard of Wor (USA, Europe)"}, "1c365a50": {"crc32": "0x1c365a50", "crc32_128kb": "0x1c365a50", "region": "NTSC-U", "release_name": "Final Cartridge, The (USA, Europe) (Program)", "title": "Final Cartridge, The (USA, Europe)"}, "1c3d258f": {"crc32": "0x1c3d258f", "crc32_128kb": "0x1c3d258f", "region": "NTSC-U", "release_name": "Fix-It Felix Jr. (World) (Aftermarket) (Unl)", "title": "Fix-It Felix Jr."}, "1e1ec26f": {"crc32": "0x1e1ec26f", "crc32_128kb": "0x1e1ec26f", "region": "NTSC-U", "release_name": "Coco Notes (USA, Europe)", "title": "Coco Notes (USA, Europe)"}, "1e394b6c": {"crc32": "0x1e394b6c", "crc32_128kb": "0x1e394b6c", "region": "NTSC-U", "release_name": "Calc Result - The Spread Sheet - Easy (USA, Europe) (Program) (ECRBLU)", "title": "Calc Result - The Spread Sheet - Easy (USA, Europe) (ECRBLU)"}, "1ef5fc6c": {"crc32": "0x1ef5fc6c", "crc32_128kb": "0x1ef5fc6c", "region": "NTSC-U", "release_name": "Jupiter Lander (World) (v02) (MAX)", "title": "Jupiter Lander (v02) (MAX)"}, "22fec00f": {"crc32": "0x22fec00f", "crc32_128kb": "0x22fec00f", "region": "NTSC-U", "release_name": "Fraction Fever (USA, Europe)", "title": "Fraction Fever (USA, Europe)"}, "254edb67": {"crc32": "0x254edb67", "crc32_128kb": "0x254edb67", "region": "NTSC-U", "release_name": "BC's Quest for Tires (USA, Europe)", "title": "BC's Quest for Tires (USA, Europe)"}, "25c99a74": {"crc32": "0x25c99a74", "crc32_128kb": "0x25c99a74", "region": "NTSC-U", "release_name": "Diary 64 (USA, Europe) (Program)", "title": "Diary 64 (USA, Europe)"}, "2724ab7e": {"crc32": "0x2724ab7e", "crc32_128kb": "0x2724ab7e", "region": "NTSC-U", "release_name": "Story Machine (USA, Europe)", "title": "Story Machine (USA, Europe)"}, "29424408": {"crc32": "0x29424408", "crc32_128kb": "0x29424408", "region": "NTSC-U", "release_name": "Ranch (USA, Europe)", "title": "Ranch (USA, Europe)"}, "294411f6": {"crc32": "0x294411f6", "crc32_128kb": "0x294411f6", "region": "NTSC-U", "release_name": "Toy Bizarre (USA, Europe)", "title": "Toy Bizarre (USA, Europe)"}, "298f8024": {"crc32": "0x298f8024", "crc32_128kb": "0x298f8024", "region": "NTSC-U", "release_name": "Tank Wars (USA, Europe)", "title": "Tank Wars (USA, Europe)"}, "2a02b1a1": {"crc32": "0x2a02b1a1", "crc32_128kb": "0x2a02b1a1", "region": "NTSC-U", "release_name": "Vindicators (USA, Europe)", "title": "Vindicators (USA, Europe)"}, "2aa90a28": {"crc32": "0x2aa90a28", "crc32_128kb": "0x2aa90a28", "region": "NTSC-U", "release_name": "Graf 64 (USA, Europe) (Program)", "title": "Graf 64 (USA, Europe)"}, "2bc5c748": {"crc32": "0x2bc5c748", "crc32_128kb": "0x2bc5c748", "region": "NTSC-J", "release_name": "Money Wars (Japan) (v01) (MAX)", "title": "Money Wars (v01) (MAX)"}, "2bcd3c61": {"crc32": "0x2bcd3c61", "crc32_128kb": "0x2bcd3c61", "region": "NTSC-U", "release_name": "Minnesota Fat's Pool Challenger (USA)", "title": "Minnesota Fat's Pool Challenger"}, "2c0aa0f2": {"crc32": "0x2c0aa0f2", "crc32_128kb": "0x2c0aa0f2", "region": "NTSC-U", "release_name": "Commodore 64 Diagnostic (USA, Europe) (Program)", "title": "Commodore 64 Diagnostic (USA, Europe)"}, "2c3ff33e": {"crc32": "0x2c3ff33e", "crc32_128kb": "0x2c3ff33e", "region": "NTSC-U", "release_name": "Kindercomp (USA, Europe)", "title": "Kindercomp (USA, Europe)"}, "2ccf3fe4": {"crc32": "0x2ccf3fe4", "crc32_128kb": "0x2ccf3fe4", "region": "NTSC-U", "release_name": "Bug Crusher (USA, Europe)", "title": "Bug Crusher (USA, Europe)"}, "2e4f7244": {"crc32": "0x2e4f7244", "crc32_128kb": "0x2e4f7244", "region": "NTSC-U", "release_name": "Super Zaxxon (USA, Europe)", "title": "Super Zaxxon (USA, Europe)"}, "2ee2937d": {"crc32": "0x2ee2937d", "crc32_128kb": "0x2ee2937d", "region": "NTSC-U", "release_name": "Music Composer (World) (MAX)", "title": "Music Composer (MAX)"}, "2f2615f3": {"crc32": "0x2f2615f3", "crc32_128kb": "0x2f2615f3", "region": "NTSC-U", "release_name": "Juice! (USA, Europe)", "title": "Juice! (USA, Europe)"}, "325c9305": {"crc32": "0x325c9305", "crc32_128kb": "0x325c9305", "region": "NTSC-U", "release_name": "Park Patrol (USA, Europe)", "title": "Park Patrol (USA, Europe)"}, "325ecfcc": {"crc32": "0x325ecfcc", "crc32_128kb": "0x325ecfcc", "region": "NTSC-U", "release_name": "Donkey Kong (USA, Europe)", "title": "Donkey Kong (USA, Europe)"}, "3281c3bb": {"crc32": "0x3281c3bb", "crc32_128kb": "0x4ef88ba0", "region": "NTSC-U", "release_name": "Expert, The (USA, Europe) (Program) (Expert21)", "title": "Expert, The (USA, Europe) (Expert21)"}, "33007075": {"crc32": "0x33007075", "crc32_128kb": "0x33007075", "region": "NTSC-U", "release_name": "Don't Block The Box! (World) (Aftermarket) (Unl)", "title": "Don't Block The Box!"}, "355a9299": {"crc32": "0x355a9299", "crc32_128kb": "0x355a9299", "region": "NTSC-U", "release_name": "Designer's Pencil, The (USA, Europe) (Program)", "title": "Designer's Pencil, The (USA, Europe)"}, "35d997e1": {"crc32": "0x35d997e1", "crc32_128kb": "0x67a65abe", "region": "NTSC-U", "release_name": "10x10 (World) (Aftermarket) (Unl)", "title": "10x10"}, "360bc828": {"crc32": "0x360bc828", "crc32_128kb": "0x360bc828", "region": "NTSC-J", "release_name": "Super Alien (Japan) (v01) (MAX)", "title": "Super Alien (v01) (MAX)"}, "37a8cd4b": {"crc32": "0x37a8cd4b", "crc32_128kb": "0x37a8cd4b", "region": "NTSC-U", "release_name": "Congo Bongo (USA, Europe)", "title": "Congo Bongo (USA, Europe)"}, "38016807": {"crc32": "0x38016807", "crc32_128kb": "0x38016807", "region": "NTSC-U", "release_name": "Space Ric-O-Shay (USA, Europe)", "title": "Space Ric-O-Shay (USA, Europe)"}, "3b981a91": {"crc32": "0x3b981a91", "crc32_128kb": "0x3b981a91", "region": "NTSC-U", "release_name": "Tooth Invaders (USA, Europe)", "title": "Tooth Invaders (USA, Europe)"}, "3be1ca96": {"crc32": "0x3be1ca96", "crc32_128kb": "0x3be1ca96", "region": "NTSC-U", "release_name": "Electronic Mailbox-64 (USA, Europe) (Program)", "title": "Electronic Mailbox-64 (USA, Europe)"}, "3dc43ab1": {"crc32": "0x3dc43ab1", "crc32_128kb": "0x3dc43ab1", "region": "NTSC-U", "release_name": "Pagefox (Finland) (Program) (u2)", "title": "Pagefox (Finland) (u2)"}, "3dfca6e7": {"crc32": "0x3dfca6e7", "crc32_128kb": "0x3dfca6e7", "region": "NTSC-U", "release_name": "Timebound (USA, Europe)", "title": "Timebound (USA, Europe)"}, "3e279184": {"crc32": "0x3e279184", "crc32_128kb": "0xc69a48ca", "region": "NTSC-U", "release_name": "Rechtschreiblowe, Der - Fit in Rechtschreibung - 3.-4. Schuljahr (Germany) (Teil 2)", "title": "Rechtschreiblowe, Der - Fit in Rechtschreibung - 3.-4. Schuljahr (Germany) (Teil 2)"}, "3ed61a8e": {"crc32": "0x3ed61a8e", "crc32_128kb": "0x3ed61a8e", "region": "NTSC-U", "release_name": "Super Expander 64 (USA, Europe) (Program)", "title": "Super Expander 64 (USA, Europe)"}, "3ef0b782": {"crc32": "0x3ef0b782", "crc32_128kb": "0x3ef0b782", "region": "NTSC-U", "release_name": "Clowns (World) (En,Ja) (v02) (MAX) (2)", "title": "Clowns (En,Ja) (v02) (MAX) (2)"}, "4034f09f": {"crc32": "0x4034f09f", "crc32_128kb": "0x4034f09f", "region": "NTSC-U", "release_name": "Hop Along Counting (USA, Europe)", "title": "Hop Along Counting (USA, Europe)"}, "41288ef8": {"crc32": "0x41288ef8", "crc32_128kb": "0xfcb7ba01", "region": "NTSC-U", "release_name": "Ninja Remix (USA, Europe)", "title": "Ninja Remix (USA, Europe)"}, "41a40ecb": {"crc32": "0x41a40ecb", "crc32_128kb": "0x278aa7ef", "region": "NTSC-U", "release_name": "Rechtschreiblowe, Der - Fit in Rechtschreibung - 3.-4. Schuljahr (Germany) (Teil 3)", "title": "Rechtschreiblowe, Der - Fit in Rechtschreibung - 3.-4. Schuljahr (Germany) (Teil 3)"}, "41c93c88": {"crc32": "0x41c93c88", "crc32_128kb": "0x41c93c88", "region": "NTSC-U", "release_name": "Paper Planes (World) (Aftermarket) (Unl)", "title": "Paper Planes"}, "4506e0f7": {"crc32": "0x4506e0f7", "crc32_128kb": "0x4506e0f7", "region": "NTSC-U", "release_name": "Kids on Keys (USA, Europe)", "title": "Kids on Keys (USA, Europe)"}, "460b6c0d": {"crc32": "0x460b6c0d", "crc32_128kb": "0xcaa5d01c", "region": "NTSC-U", "release_name": "Expert, The (USA, Europe) (Program) (Expert32)", "title": "Expert, The (USA, Europe) (Expert32)"}, "4613dc2e": {"crc32": "0x4613dc2e", "crc32_128kb": "0x4613dc2e", "region": "NTSC-U", "release_name": "Gridrunner (USA, Europe)", "title": "Gridrunner (USA, Europe)"}, "47d3d8cc": {"crc32": "0x47d3d8cc", "crc32_128kb": "0x47d3d8cc", "region": "NTSC-U", "release_name": "Aegean Voyage (USA, Europe)", "title": "Aegean Voyage (USA, Europe)"}, "4843e4d8": {"crc32": "0x4843e4d8", "crc32_128kb": "0x4843e4d8", "region": "NTSC-U", "release_name": "Hypra-Disk-Modul II (Germany) (Program)", "title": "Hypra-Disk-Modul II (Germany)"}, "48cf411a": {"crc32": "0x48cf411a", "crc32_128kb": "0x51d782e4", "region": "NTSC-U", "release_name": "Narco Police (USA, Europe)", "title": "Narco Police (USA, Europe)"}, "495d0046": {"crc32": "0x495d0046", "crc32_128kb": "0xaba3ab6e", "region": "NTSC-U", "release_name": "Expert, The (USA, Europe) (Program) (Ex32u)", "title": "Expert, The (USA, Europe) (Ex32u)"}, "4a07706e": {"crc32": "0x4a07706e", "crc32_128kb": "0x4a07706e", "region": "NTSC-U", "release_name": "Kickman (World) (v03) (MAX)", "title": "Kickman (v03) (MAX)"}, "4a268aab": {"crc32": "0x4a268aab", "crc32_128kb": "0x4a268aab", "region": "NTSC-U", "release_name": "River Raid (USA, Europe)", "title": "River Raid (USA, Europe)"}, "4a29dbeb": {"crc32": "0x4a29dbeb", "crc32_128kb": "0x8756cc6c", "region": "NTSC-U", "release_name": "Galaxian DX (World) (Aftermarket) (Unl)", "title": "Galaxian DX"}, "4b0db110": {"crc32": "0x4b0db110", "crc32_128kb": "0x4b0db110", "region": "NTSC-U", "release_name": "Coccinelle cherche dessinateur (France)", "title": "Coccinelle cherche dessinateur (France)"}, "4b211f27": {"crc32": "0x4b211f27", "crc32_128kb": "0x4b211f27", "region": "NTSC-U", "release_name": "Popeye (USA, Europe)", "title": "Popeye (USA, Europe)"}, "4b6cc7d9": {"crc32": "0x4b6cc7d9", "crc32_128kb": "0xb7756ab7", "region": "NTSC-U", "release_name": "Galaga (World) (v1.06) (Aftermarket) (Unl)", "title": "Galaga (v1.06)"}, "4b8d4baf": {"crc32": "0x4b8d4baf", "crc32_128kb": "0x4b8d4baf", "region": "NTSC-U", "release_name": "Logic Levels (USA, Europe)", "title": "Logic Levels (USA, Europe)"}, "4d37b6e1": {"crc32": "0x4d37b6e1", "crc32_128kb": "0x4d37b6e1", "region": "NTSC-U", "release_name": "Peanut Butter Panic (USA, Europe)", "title": "Peanut Butter Panic (USA, Europe)"}, "4dccd7fa": {"crc32": "0x4dccd7fa", "crc32_128kb": "0x4dccd7fa", "region": "NTSC-U", "release_name": "Hyper Harvest (World) (Aftermarket) (Unl)", "title": "Hyper Harvest"}, "502fc7f8": {"crc32": "0x502fc7f8", "crc32_128kb": "0x502fc7f8", "region": "NTSC-U", "release_name": "Adventure Creator (USA, Europe)", "title": "Adventure Creator (USA, Europe)"}, "5061aeb4": {"crc32": "0x5061aeb4", "crc32_128kb": "0xae4129fe", "region": "NTSC-U", "release_name": "Megamania (World) (Aftermarket) (Unl)", "title": "Megamania"}, "51b75bf0": {"crc32": "0x51b75bf0", "crc32_128kb": "0x51b75bf0", "region": "NTSC-U", "release_name": "Linking Logic (USA, Europe)", "title": "Linking Logic (USA, Europe)"}, "51cf1a85": {"crc32": "0x51cf1a85", "crc32_128kb": "0x51cf1a85", "region": "NTSC-U", "release_name": "Leader Board - Pro Golf Simulator (USA, Europe)", "title": "Leader Board - Pro Golf Simulator (USA, Europe)"}, "51e079b5": {"crc32": "0x51e079b5", "crc32_128kb": "0x51e079b5", "region": "NTSC-U", "release_name": "Ducks Ahoy! (USA, Europe)", "title": "Ducks Ahoy! (USA, Europe)"}, "523c56c1": {"crc32": "0x523c56c1", "crc32_128kb": "0x523c56c1", "region": "NTSC-J", "release_name": "Bowling (Japan) (MAX)", "title": "Bowling (MAX)"}, "5291b664": {"crc32": "0x5291b664", "crc32_128kb": "0x5291b664", "region": "NTSC-U", "release_name": "Tenpins (USA, Europe)", "title": "Tenpins (USA, Europe)"}, "52c27b4f": {"crc32": "0x52c27b4f", "crc32_128kb": "0x52c27b4f", "region": "NTSC-U", "release_name": "Format- und Hardcopymodul (Germany) (Program)", "title": "Format- und Hardcopymodul (Germany)"}, "52e9d37b": {"crc32": "0x52e9d37b", "crc32_128kb": "0x52e9d37b", "region": "NTSC-U", "release_name": "Mr. Cool (USA, Europe)", "title": "Mr. Cool (USA, Europe)"}, "5356af90": {"crc32": "0x5356af90", "crc32_128kb": "0x5356af90", "region": "NTSC-J", "release_name": "Avenger (Japan) (v02) (MAX)", "title": "Avenger (v02) (MAX)"}, "53c7f4cf": {"crc32": "0x53c7f4cf", "crc32_128kb": "0x53c7f4cf", "region": "NTSC-U", "release_name": "Jumpman Junior (USA, Europe)", "title": "Jumpman Junior (USA, Europe)"}, "53da6527": {"crc32": "0x53da6527", "crc32_128kb": "0x53da6527", "region": "NTSC-U", "release_name": "Seafox (USA, Europe)", "title": "Seafox (USA, Europe)"}, "543adccc": {"crc32": "0x543adccc", "crc32_128kb": "0x543adccc", "region": "NTSC-U", "release_name": "Pipes (USA, Europe)", "title": "Pipes (USA, Europe)"}, "54e485a4": {"crc32": "0x54e485a4", "crc32_128kb": "0x52071f5d", "region": "PAL", "release_name": "Myth (Europe)", "title": "Myth"}, "55416f3a": {"crc32": "0x55416f3a", "crc32_128kb": "0x55416f3a", "region": "PAL", "release_name": "Action Replay Professional (Europe) (v4.2) (Program) (Unl)", "title": "Action Replay Professional (v4.2)"}, "55a2c9c7": {"crc32": "0x55a2c9c7", "crc32_128kb": "0x55a2c9c7", "region": "NTSC-U", "release_name": "Ghostbusters (USA, Europe)", "title": "Ghostbusters (USA, Europe)"}, "5604784f": {"crc32": "0x5604784f", "crc32_128kb": "0x5604784f", "region": "NTSC-U", "release_name": "Rechenlowe, Der - Fit in Addition und Subtraktion - 3.-4. Schuljahr (Germany)", "title": "Rechenlowe, Der - Fit in Addition und Subtraktion - 3.-4. Schuljahr (Germany)"}, "56ee0efe": {"crc32": "0x56ee0efe", "crc32_128kb": "0x56ee0efe", "region": "PAL", "release_name": "Action Replay Professional (Europe) (v6.0) (Program) (Unl)", "title": "Action Replay Professional (v6.0)"}, "572029ac": {"crc32": "0x572029ac", "crc32_128kb": "0x572029ac", "region": "NTSC-U", "release_name": "Webster - The Word Game (USA, Europe)", "title": "Webster - The Word Game (USA, Europe)"}, "58aaf201": {"crc32": "0x58aaf201", "crc32_128kb": "0x58aaf201", "region": "NTSC-U", "release_name": "Close Encounters of the Worst Kind (USA, Europe)", "title": "Close Encounters of the Worst Kind (USA, Europe)"}, "5a9fe981": {"crc32": "0x5a9fe981", "crc32_128kb": "0x5a9fe981", "region": "NTSC-U", "release_name": "128er Quickload (USA, Europe) (Program)", "title": "128er Quickload (USA, Europe)"}, "5c4526ba": {"crc32": "0x5c4526ba", "crc32_128kb": "0x0b7b11dc", "region": "NTSC-U", "release_name": "Expert, The (USA, Europe) (Program) (Ex32)", "title": "Expert, The (USA, Europe) (Ex32)"}, "5e3dc6f7": {"crc32": "0x5e3dc6f7", "crc32_128kb": "0x5e3dc6f7", "region": "NTSC-U", "release_name": "Dance Fantasy (USA, Europe)", "title": "Dance Fantasy (USA, Europe)"}, "5e46f33d": {"crc32": "0x5e46f33d", "crc32_128kb": "0x523b76e6", "region": "NTSC-U", "release_name": "Pillars (World) (Aftermarket) (Unl)", "title": "Pillars"}, "5e4ba52d": {"crc32": "0x5e4ba52d", "crc32_128kb": "0x5e4ba52d", "region": "NTSC-U", "release_name": "Star Ranger (USA, Europe)", "title": "Star Ranger (USA, Europe)"}, "5fb3e89c": {"crc32": "0x5fb3e89c", "crc32_128kb": "0x5fb3e89c", "region": "NTSC-U", "release_name": "Super Snapshot 5 (USA) (Program)", "title": "Super Snapshot 5"}, "5fe07c45": {"crc32": "0x5fe07c45", "crc32_128kb": "0x5fe07c45", "region": "NTSC-U", "release_name": "Wizard of Id's Wiztype, The (USA, Europe)", "title": "Wizard of Id's Wiztype, The (USA, Europe)"}, "60eba43d": {"crc32": "0x60eba43d", "crc32_128kb": "0x60eba43d", "region": "NTSC-J", "release_name": "Omega Race (Japan) (v02) (MAX)", "title": "Omega Race (v02) (MAX)"}, "6218c08e": {"crc32": "0x6218c08e", "crc32_128kb": "0x6218c08e", "region": "NTSC-U", "release_name": "Diamond Mine (USA, Europe)", "title": "Diamond Mine (USA, Europe)"}, "64dc08b0": {"crc32": "0x64dc08b0", "crc32_128kb": "0x64dc08b0", "region": "NTSC-U", "release_name": "Warp Speed (USA, Europe) (v1) (Program)", "title": "Warp Speed (USA, Europe) (v1)"}, "6551ffc7": {"crc32": "0x6551ffc7", "crc32_128kb": "0x455b48a3", "region": "PAL", "release_name": "RoboCop 3 (Europe)", "title": "RoboCop 3"}, "6598c9d1": {"crc32": "0x6598c9d1", "crc32_128kb": "0x6598c9d1", "region": "NTSC-U", "release_name": "Magic Formel (USA, Europe) (v1.2) (Program)", "title": "Magic Formel (USA, Europe)"}, "65fa2c3d": {"crc32": "0x65fa2c3d", "crc32_128kb": "0xf8ed36f4", "region": "PAL", "release_name": "Navy SEALs (Europe)", "title": "Navy SEALs"}, "67875150": {"crc32": "0x67875150", "crc32_128kb": "0x67875150", "region": "NTSC-U", "release_name": "Calc Result - The Spread Sheet - Advanced (USA, Europe) (Program)", "title": "Calc Result - The Spread Sheet - Advanced (USA, Europe)"}, "686baf97": {"crc32": "0x686baf97", "crc32_128kb": "0x686baf97", "region": "NTSC-U", "release_name": "Number Nabber, Shape Grabber (USA, Europe)", "title": "Number Nabber, Shape Grabber (USA, Europe)"}, "68cd1077": {"crc32": "0x68cd1077", "crc32_128kb": "0x68cd1077", "region": "NTSC-U", "release_name": "Warp Speed (USA, Europe) (v2.0) (Program)", "title": "Warp Speed (USA, Europe) (v2.0)"}, "69734b98": {"crc32": "0x69734b98", "crc32_128kb": "0x69734b98", "region": "NTSC-U", "release_name": "Final Cartridge III, The (USA, Europe) (Dec 88) (Program)", "title": "Final Cartridge III, The (USA, Europe) (Dec 88)"}, "6aff7777": {"crc32": "0x6aff7777", "crc32_128kb": "0x6aff7777", "region": "NTSC-U", "release_name": "Muistio 64 (Finland) (Program)", "title": "Muistio 64 (Finland)"}, "6b12d4e9": {"crc32": "0x6b12d4e9", "crc32_128kb": "0x6b12d4e9", "region": "NTSC-U", "release_name": "Rechenlowe, Der - Fit in Addition und Subtraktion - 2.-3. Schuljahr (Germany)", "title": "Rechenlowe, Der - Fit in Addition und Subtraktion - 2.-3. Schuljahr (Germany)"}, "6cbbd29f": {"crc32": "0x6cbbd29f", "crc32_128kb": "0x6cbbd29f", "region": "NTSC-U", "release_name": "Super Smash (USA, Europe)", "title": "Super Smash (USA, Europe)"}, "6cce06eb": {"crc32": "0x6cce06eb", "crc32_128kb": "0x6cce06eb", "region": "NTSC-U", "release_name": "Serpentine (USA, Europe)", "title": "Serpentine (USA, Europe)"}, "6d8f51a4": {"crc32": "0x6d8f51a4", "crc32_128kb": "0x6d8f51a4", "region": "NTSC-U", "release_name": "Frogger (USA, Europe)", "title": "Frogger (USA, Europe)"}, "6e56aba1": {"crc32": "0x6e56aba1", "crc32_128kb": "0x6e56aba1", "region": "NTSC-J", "release_name": "Clowns (Japan) (v01) (MAX)", "title": "Clowns (v01) (MAX)"}, "6fbf905d": {"crc32": "0x6fbf905d", "crc32_128kb": "0x6fbf905d", "region": "NTSC-U", "release_name": "Avenger (USA, Europe) (v03) (MAX)", "title": "Avenger (USA, Europe) (v03) (MAX)"}, "71b6d7e3": {"crc32": "0x71b6d7e3", "crc32_128kb": "0x71b6d7e3", "region": "NTSC-U", "release_name": "Falconian Invaders (USA, Europe)", "title": "Falconian Invaders (USA, Europe)"}, "71c621c6": {"crc32": "0x71c621c6", "crc32_128kb": "0x71c621c6", "region": "NTSC-U", "release_name": "Paint Brush (USA, Europe)", "title": "Paint Brush (USA, Europe)"}, "71e9f4f7": {"crc32": "0x71e9f4f7", "crc32_128kb": "0x71e9f4f7", "region": "NTSC-U", "release_name": "Mario's Brewery (USA, Europe)", "title": "Mario's Brewery (USA, Europe)"}, "72d827a9": {"crc32": "0x72d827a9", "crc32_128kb": "0xb1bd5802", "region": "NTSC-U", "release_name": "Expert, The (USA, Europe) (Program) (Utility)", "title": "Expert, The (USA, Europe) (Utility)"}, "7427d210": {"crc32": "0x7427d210", "crc32_128kb": "0x7427d210", "region": "NTSC-U", "release_name": "Zenji (USA, Europe)", "title": "Zenji (USA, Europe)"}, "742e5f29": {"crc32": "0x742e5f29", "crc32_128kb": "0x742e5f29", "region": "NTSC-J", "release_name": "Radar Rat Race (Japan) (v02) (MAX)", "title": "Radar Rat Race (v02) (MAX)"}, "75401b26": {"crc32": "0x75401b26", "crc32_128kb": "0x75401b26", "region": "NTSC-U", "release_name": "256K-EPROM-System (Germany) (v5) (Program)", "title": "256K-EPROM-System (Germany) (v5)"}, "75ba8dbf": {"crc32": "0x75ba8dbf", "crc32_128kb": "0x75ba8dbf", "region": "NTSC-U", "release_name": "Tennis (USA) (VICE)", "title": "Tennis (VICE)"}, "775bcc8a": {"crc32": "0x775bcc8a", "crc32_128kb": "0x775bcc8a", "region": "NTSC-U", "release_name": "Up'n Down (USA, Europe)", "title": "Up'n Down (USA, Europe)"}, "785b37c8": {"crc32": "0x785b37c8", "crc32_128kb": "0x785b37c8", "region": "NTSC-U", "release_name": "Miner 2049er Starring Bounty Bob (USA, Europe)", "title": "Miner 2049er Starring Bounty Bob (USA, Europe)"}, "7930b863": {"crc32": "0x7930b863", "crc32_128kb": "0x7930b863", "region": "NTSC-U", "release_name": "Dragonsden (USA, Europe)", "title": "Dragonsden (USA, Europe)"}, "797ee423": {"crc32": "0x797ee423", "crc32_128kb": "0x797ee423", "region": "NTSC-U", "release_name": "Expert, The (USA, Europe) (Program)", "title": "Expert, The (USA, Europe)"}, "79a06d81": {"crc32": "0x79a06d81", "crc32_128kb": "0x79a06d81", "region": "NTSC-U", "release_name": "Speed Math & Bingo Math (USA, Europe) (v01) (MAX)", "title": "Speed Math & Bingo Math (USA, Europe) (v01) (MAX)"}, "7aa53acb": {"crc32": "0x7aa53acb", "crc32_128kb": "0x7aa53acb", "region": "NTSC-U", "release_name": "Super Explode 5 (USA, Europe) (Program)", "title": "Super Explode 5 (USA, Europe)"}, "7b8f0d44": {"crc32": "0x7b8f0d44", "crc32_128kb": "0x7b8f0d44", "region": "NTSC-U", "release_name": "Human Skeleton Tutorial (USA)", "title": "Human Skeleton Tutorial"}, "7c299a2e": {"crc32": "0x7c299a2e", "crc32_128kb": "0x7c299a2e", "region": "NTSC-U", "release_name": "Rack 'em Up! (USA, Europe)", "title": "Rack 'em Up! (USA, Europe)"}, "7c2e0cc1": {"crc32": "0x7c2e0cc1", "crc32_128kb": "0x7c2e0cc1", "region": "NTSC-U", "release_name": "Megamania (World) (Aftermarket) (Unl)", "title": "Megamania"}, "7d08516f": {"crc32": "0x7d08516f", "crc32_128kb": "0x7d08516f", "region": "NTSC-U", "release_name": "Song Maker (USA, Europe)", "title": "Song Maker (USA, Europe)"}, "7d44fba2": {"crc32": "0x7d44fba2", "crc32_128kb": "0x7d44fba2", "region": "NTSC-U", "release_name": "Jukebox (USA, Europe)", "title": "Jukebox (USA, Europe)"}, "7dbe3728": {"crc32": "0x7dbe3728", "crc32_128kb": "0x7dbe3728", "region": "NTSC-U", "release_name": "Star Trek - Strategic Operations Simulator (USA, Europe)", "title": "Star Trek - Strategic Operations Simulator (USA, Europe)"}, "7fac69b2": {"crc32": "0x7fac69b2", "crc32_128kb": "0x7fac69b2", "region": "NTSC-U", "release_name": "HES Writer 64 (USA, Europe) (Program)", "title": "HES Writer 64 (USA, Europe)"}, "805e8c5f": {"crc32": "0x805e8c5f", "crc32_128kb": "0x805e8c5f", "region": "NTSC-U", "release_name": "Espial (USA, Europe)", "title": "Espial (USA, Europe)"}, "808f8148": {"crc32": "0x808f8148", "crc32_128kb": "0x808f8148", "region": "NTSC-U", "release_name": "Attack of the Mutant Camels (USA)", "title": "Attack of the Mutant Camels"}, "81489ef4": {"crc32": "0x81489ef4", "crc32_128kb": "0x81489ef4", "region": "NTSC-U", "release_name": "Pitfall! (USA, Europe)", "title": "Pitfall! (USA, Europe)"}, "82b1c134": {"crc32": "0x82b1c134", "crc32_128kb": "0x82b1c134", "region": "NTSC-U", "release_name": "HES Mon 64 (USA, Europe) (Program)", "title": "HES Mon 64 (USA, Europe)"}, "82b9587f": {"crc32": "0x82b9587f", "crc32_128kb": "0x82b9587f", "region": "NTSC-U", "release_name": "Moondust (USA, Europe)", "title": "Moondust (USA, Europe)"}, "82e2e4a0": {"crc32": "0x82e2e4a0", "crc32_128kb": "0x82e2e4a0", "region": "PAL", "release_name": "Super Snapshot 5 (Europe) (Program)", "title": "Super Snapshot 5"}, "83e34e6c": {"crc32": "0x83e34e6c", "crc32_128kb": "0x83e34e6c", "region": "NTSC-U", "release_name": "Sesame Street - Letter-Go-Round (USA, Europe)", "title": "Sesame Street - Letter-Go-Round (USA, Europe)"}, "83f069bb": {"crc32": "0x83f069bb", "crc32_128kb": "0x83f069bb", "region": "NTSC-U", "release_name": "Wonder Boy (USA, Europe)", "title": "Wonder Boy (USA, Europe)"}, "8464e34f": {"crc32": "0x8464e34f", "crc32_128kb": "0x54428bc9", "region": "PAL", "release_name": "Shadow of the Beast (Europe)", "title": "Shadow of the Beast"}, "8467ca0f": {"crc32": "0x8467ca0f", "crc32_128kb": "0x8467ca0f", "region": "NTSC-U", "release_name": "Blueprint (USA, Europe)", "title": "Blueprint (USA, Europe)"}, "848282aa": {"crc32": "0x848282aa", "crc32_128kb": "0x848282aa", "region": "NTSC-U", "release_name": "Epyx Fast Load Cartridge (USA, Europe) (Program)", "title": "Epyx Fast Load Cartridge (USA, Europe)"}, "85aa080b": {"crc32": "0x85aa080b", "crc32_128kb": "0x85aa080b", "region": "NTSC-U", "release_name": "Clowns (World) (En,Ja) (v02) (MAX) (1)", "title": "Clowns (En,Ja) (v02) (MAX) (1)"}, "86cb02e3": {"crc32": "0x86cb02e3", "crc32_128kb": "0x86cb02e3", "region": "NTSC-U", "release_name": "Ultrex Quadro Maze (USA, Europe)", "title": "Ultrex Quadro Maze (USA, Europe)"}, "894c1b13": {"crc32": "0x894c1b13", "crc32_128kb": "0x894c1b13", "region": "NTSC-U", "release_name": "H.E.R.O. - Helicopter Emergency Rescue Operation (USA, Europe)", "title": "H.E.R.O. - Helicopter Emergency Rescue Operation (USA, Europe)"}, "89519613": {"crc32": "0x89519613", "crc32_128kb": "0xae0ea779", "region": "PAL", "release_name": "Terminator 2 - Judgment Day + Modern Music Maker + Image System, The (Europe)", "title": "Terminator 2 - Judgment Day + Modern Music Maker + Image System, The"}, "89fba92a": {"crc32": "0x89fba92a", "crc32_128kb": "0x1228084e", "region": "NTSC-U", "release_name": "Pillars (World) (v2.00) (Aftermarket) (Unl)", "title": "Pillars (v2.00)"}, "8b3a3235": {"crc32": "0x8b3a3235", "crc32_128kb": "0x8b3a3235", "region": "NTSC-U", "release_name": "Tennis (USA) (CCS)", "title": "Tennis (CCS)"}, "8ce482d4": {"crc32": "0x8ce482d4", "crc32_128kb": "0x8ce482d4", "region": "NTSC-U", "release_name": "Dela S-4-Modul (USA, Europe) (Program)", "title": "Dela S-4-Modul (USA, Europe)"}, "8d4c9873": {"crc32": "0x8d4c9873", "crc32_128kb": "0x8d4c9873", "region": "NTSC-U", "release_name": "Tapper (USA, Europe)", "title": "Tapper (USA, Europe)"}, "8e3e34e2": {"crc32": "0x8e3e34e2", "crc32_128kb": "0x8e3e34e2", "region": "NTSC-U", "release_name": "Happy-Packer (Germany) (Program)", "title": "Happy-Packer (Germany)"}, "910a9d74": {"crc32": "0x910a9d74", "crc32_128kb": "0x910a9d74", "region": "NTSC-U", "release_name": "Jawbreaker (USA, Europe)", "title": "Jawbreaker (USA, Europe)"}, "913afd77": {"crc32": "0x913afd77", "crc32_128kb": "0x913afd77", "region": "NTSC-U", "release_name": "Rechenlowe, Der - Fit in Geometrie - 3.-4. Schuljahr (Germany)", "title": "Rechenlowe, Der - Fit in Geometrie - 3.-4. Schuljahr (Germany)"}, "927793ec": {"crc32": "0x927793ec", "crc32_128kb": "0x927793ec", "region": "NTSC-U", "release_name": "Calc Result - The Spread Sheet - Easy (USA, Europe) (Program) (Alt) (hn613128)", "title": "Calc Result - The Spread Sheet - Easy (USA, Europe) (hn613128)"}, "9318593f": {"crc32": "0x9318593f", "crc32_128kb": "0x9318593f", "region": "NTSC-U", "release_name": "Sammy Lightfoot (USA, Europe)", "title": "Sammy Lightfoot (USA, Europe)"}, "948d7fd0": {"crc32": "0x948d7fd0", "crc32_128kb": "0x948d7fd0", "region": "NTSC-J", "release_name": "MAX BASIC (Japan) (MAX)", "title": "MAX BASIC (MAX)"}, "961e38fc": {"crc32": "0x961e38fc", "crc32_128kb": "0x961e38fc", "region": "NTSC-U", "release_name": "Adventure 3 - The Fourth Sarcophagus (USA, Europe)", "title": "Adventure 3 - The Fourth Sarcophagus (USA, Europe)"}, "963e3859": {"crc32": "0x963e3859", "crc32_128kb": "0xb9a416fe", "region": "PAL", "release_name": "Space Gun (Europe)", "title": "Space Gun"}, "96be8043": {"crc32": "0x96be8043", "crc32_128kb": "0x10220ddd", "region": "PAL", "release_name": "MicroProse Soccer + Rick Dangerous + Stunt Car Racer (Europe) (Power Play)", "title": "MicroProse Soccer + Rick Dangerous + Stunt Car Racer (Power Play)"}, "96cd7f72": {"crc32": "0x96cd7f72", "crc32_128kb": "0x96cd7f72", "region": "NTSC-U", "release_name": "Math Mileage (USA, Europe)", "title": "Math Mileage (USA, Europe)"}, "97130687": {"crc32": "0x97130687", "crc32_128kb": "0x97130687", "region": "NTSC-U", "release_name": "Lazarian (USA, Europe)", "title": "Lazarian (USA, Europe)"}, "99072c64": {"crc32": "0x99072c64", "crc32_128kb": "0x99072c64", "region": "NTSC-U", "release_name": "Dot Gobbler (USA, Europe) (Alt)", "title": "Dot Gobbler (USA, Europe)"}, "9a53961f": {"crc32": "0x9a53961f", "crc32_128kb": "0x9a53961f", "region": "NTSC-U", "release_name": "MasterType (USA, Europe)", "title": "MasterType (USA, Europe)"}, "9a5435ce": {"crc32": "0x9a5435ce", "crc32_128kb": "0x9a5435ce", "region": "NTSC-U", "release_name": "Space Action (USA, Europe)", "title": "Space Action (USA, Europe)"}, "9b07e706": {"crc32": "0x9b07e706", "crc32_128kb": "0x9b07e706", "region": "NTSC-U", "release_name": "Moon Patrol (USA, Europe)", "title": "Moon Patrol (USA, Europe)"}, "9c2643bf": {"crc32": "0x9c2643bf", "crc32_128kb": "0x9c2643bf", "region": "NTSC-U", "release_name": "Choplifter! (USA, Europe)", "title": "Choplifter! (USA, Europe)"}, "9c310d18": {"crc32": "0x9c310d18", "crc32_128kb": "0x2069f4f9", "region": "PAL", "release_name": "Battle Command (Europe)", "title": "Battle Command"}, "9d87a042": {"crc32": "0x9d87a042", "crc32_128kb": "0x9d87a042", "region": "NTSC-U", "release_name": "Ms. Pac-Man (USA, Europe) (1)", "title": "Ms. Pac-Man (USA, Europe) (1)"}, "9ebe3620": {"crc32": "0x9ebe3620", "crc32_128kb": "0x9ebe3620", "region": "NTSC-U", "release_name": "Maze Master (USA, Europe)", "title": "Maze Master (USA, Europe)"}, "9f2d74aa": {"crc32": "0x9f2d74aa", "crc32_128kb": "0x9f2d74aa", "region": "NTSC-U", "release_name": "International Football (USA, Europe)", "title": "International Football (USA, Europe)"}, "a0c98111": {"crc32": "0xa0c98111", "crc32_128kb": "0xa0c98111", "region": "NTSC-U", "release_name": "Ms. Pac-Man (USA, Europe) (2)", "title": "Ms. Pac-Man (USA, Europe) (2)"}, "a17c6602": {"crc32": "0xa17c6602", "crc32_128kb": "0xa17c6602", "region": "NTSC-J", "release_name": "Mole Attack (Japan) (v01) (MAX)", "title": "Mole Attack (v01) (MAX)"}, "a19206fc": {"crc32": "0xa19206fc", "crc32_128kb": "0xa19206fc", "region": "NTSC-U", "release_name": "Dancing Feats (USA, Europe)", "title": "Dancing Feats (USA, Europe)"}, "a211bbaa": {"crc32": "0xa211bbaa", "crc32_128kb": "0xa211bbaa", "region": "NTSC-U", "release_name": "Rechenlowe, Der - Fit in Mathematik - 1. Schuljahr (Germany)", "title": "Rechenlowe, Der - Fit in Mathematik - 1. Schuljahr (Germany)"}, "a280c09f": {"crc32": "0xa280c09f", "crc32_128kb": "0xa280c09f", "region": "NTSC-U", "release_name": "Threshold (USA, Europe)", "title": "Threshold (USA, Europe)"}, "a2855ae7": {"crc32": "0xa2855ae7", "crc32_128kb": "0xa2855ae7", "region": "NTSC-U", "release_name": "Pac-Man (USA, Europe)", "title": "Pac-Man (USA, Europe)"}, "a2b964e4": {"crc32": "0xa2b964e4", "crc32_128kb": "0xa2b964e4", "region": "NTSC-U", "release_name": "Gateway to Apshai (USA, Europe)", "title": "Gateway to Apshai (USA, Europe)"}, "a4e1f2cc": {"crc32": "0xa4e1f2cc", "crc32_128kb": "0xa4e1f2cc", "region": "NTSC-U", "release_name": "Solar Fox (USA, Europe)", "title": "Solar Fox (USA, Europe)"}, "a5841038": {"crc32": "0xa5841038", "crc32_128kb": "0xa5841038", "region": "NTSC-U", "release_name": "Express Cartridge (USA, Europe) (Program)", "title": "Express Cartridge (USA, Europe)"}, "a6d18ee5": {"crc32": "0xa6d18ee5", "crc32_128kb": "0xa6d18ee5", "region": "NTSC-U", "release_name": "States and Capitals Tutorial (USA)", "title": "States and Capitals Tutorial"}, "a77b156e": {"crc32": "0xa77b156e", "crc32_128kb": "0xa77b156e", "region": "NTSC-U", "release_name": "Write Now! 64 (USA, Europe) (Program)", "title": "Write Now! 64 (USA, Europe)"}, "a898340c": {"crc32": "0xa898340c", "crc32_128kb": "0xa898340c", "region": "NTSC-U", "release_name": "BadLands (USA, Europe)", "title": "BadLands (USA, Europe)"}, "a8c2de66": {"crc32": "0xa8c2de66", "crc32_128kb": "0xa8c2de66", "region": "NTSC-U", "release_name": "Rechenlowe, Der - Fit in Multiplikation und Division - 2.-3. Schuljahr (Germany)", "title": "Rechenlowe, Der - Fit in Multiplikation und Division - 2.-3. Schuljahr (Germany)"}, "a8d3f7a5": {"crc32": "0xa8d3f7a5", "crc32_128kb": "0xa8d3f7a5", "region": "NTSC-U", "release_name": "Rechtschreiblowe, Der - Fit in Rechtschreibung - 3.-4. Schuljahr (Germany)", "title": "Rechtschreiblowe, Der - Fit in Rechtschreibung - 3.-4. Schuljahr (Germany)"}, "a960efbb": {"crc32": "0xa960efbb", "crc32_128kb": "0xa960efbb", "region": "NTSC-U", "release_name": "10x10 (World) (Aftermarket) (Unl)", "title": "10x10"}, "a977f2d4": {"crc32": "0xa977f2d4", "crc32_128kb": "0xa977f2d4", "region": "NTSC-U", "release_name": "Calc Result - The Spread Sheet - Easy (USA, Europe) (Program) (ECRBLK)", "title": "Calc Result - The Spread Sheet - Easy (USA, Europe) (ECRBLK)"}, "aa7cb5fc": {"crc32": "0xaa7cb5fc", "crc32_128kb": "0xaa7cb5fc", "region": "NTSC-U", "release_name": "Tyler's Dungeons (USA, Europe)", "title": "Tyler's Dungeons (USA, Europe)"}, "aaf66197": {"crc32": "0xaaf66197", "crc32_128kb": "0xaaf66197", "region": "NTSC-U", "release_name": "Doc'64 (USA, Europe) (v2.2) (Program)", "title": "Doc'64 (USA, Europe) (v2.2)"}, "ab1336ff": {"crc32": "0xab1336ff", "crc32_128kb": "0xab1336ff", "region": "NTSC-U", "release_name": "Gridrunner II - Attack of the Mutant Camels (USA)", "title": "Gridrunner II - Attack of the Mutant Camels"}, "ab1ef8b9": {"crc32": "0xab1ef8b9", "crc32_128kb": "0xab1ef8b9", "region": "NTSC-U", "release_name": "Star Wars - The Arcade Game (USA, Europe)", "title": "Star Wars - The Arcade Game (USA, Europe)"}, "ab80050c": {"crc32": "0xab80050c", "crc32_128kb": "0xab80050c", "region": "NTSC-U", "release_name": "Sea Wolf (USA, Europe) (MAX)", "title": "Sea Wolf (USA, Europe) (MAX)"}, "ad360cd4": {"crc32": "0xad360cd4", "crc32_128kb": "0xad360cd4", "region": "NTSC-U", "release_name": "Capture 2 (USA, Europe) (Program)", "title": "Capture 2 (USA, Europe)"}, "ad4e4d45": {"crc32": "0xad4e4d45", "crc32_128kb": "0xad4e4d45", "region": "NTSC-U", "release_name": "Centipede (USA, Europe) (1)", "title": "Centipede (USA, Europe) (1)"}, "af0a7526": {"crc32": "0xaf0a7526", "crc32_128kb": "0xaf0a7526", "region": "NTSC-U", "release_name": "Crisis Mountain (USA, Europe)", "title": "Crisis Mountain (USA, Europe)"}, "af3d67c8": {"crc32": "0xaf3d67c8", "crc32_128kb": "0xaf3d67c8", "region": "NTSC-U", "release_name": "Spy Hunter (USA, Europe)", "title": "Spy Hunter (USA, Europe)"}, "af9368c0": {"crc32": "0xaf9368c0", "crc32_128kb": "0xaf9368c0", "region": "NTSC-U", "release_name": "Tool-64, The (USA, Europe)", "title": "Tool-64, The (USA, Europe)"}, "af96f5b7": {"crc32": "0xaf96f5b7", "crc32_128kb": "0xaf96f5b7", "region": "NTSC-U", "release_name": "Checkers (USA, Europe)", "title": "Checkers (USA, Europe)"}, "b0490a7d": {"crc32": "0xb0490a7d", "crc32_128kb": "0xb0490a7d", "region": "NTSC-U", "release_name": "Adventure 1 - The Mutant Spiders (USA, Europe)", "title": "Adventure 1 - The Mutant Spiders (USA, Europe)"}, "b0ec1b6b": {"crc32": "0xb0ec1b6b", "crc32_128kb": "0xb0ec1b6b", "region": "NTSC-U", "release_name": "HES Mon 64 (USA, Europe) (Proto) (Program)", "title": "HES Mon 64 (USA, Europe)"}, "b2ad433e": {"crc32": "0xb2ad433e", "crc32_128kb": "0xb2ad433e", "region": "NTSC-U", "release_name": "Turbo Maze Man (USA, Europe)", "title": "Turbo Maze Man (USA, Europe)"}, "b3653175": {"crc32": "0xb3653175", "crc32_128kb": "0xb3653175", "region": "NTSC-U", "release_name": "Sea Speller (USA, Europe)", "title": "Sea Speller (USA, Europe)"}, "b4626bda": {"crc32": "0xb4626bda", "crc32_128kb": "0xb4626bda", "region": "NTSC-U", "release_name": "Financial Advisor, The (USA, Europe) (Program)", "title": "Financial Advisor, The (USA, Europe)"}, "b4b9dd54": {"crc32": "0xb4b9dd54", "crc32_128kb": "0xb4b9dd54", "region": "NTSC-U", "release_name": "Seahorse Hide'n Seek (USA, Europe)", "title": "Seahorse Hide'n Seek (USA, Europe)"}, "b54174c5": {"crc32": "0xb54174c5", "crc32_128kb": "0xb54174c5", "region": "NTSC-U", "release_name": "Infinite Space (World) (Aftermarket) (Unl)", "title": "Infinite Space"}, "b5d9c502": {"crc32": "0xb5d9c502", "crc32_128kb": "0xb5d9c502", "region": "NTSC-U", "release_name": "Pole Position (USA, Europe)", "title": "Pole Position (USA, Europe)"}, "b69f2b30": {"crc32": "0xb69f2b30", "crc32_128kb": "0x3abf8704", "region": "NTSC-U", "release_name": "Infinite Space (World) (Aftermarket) (Unl)", "title": "Infinite Space"}, "b6a803cf": {"crc32": "0xb6a803cf", "crc32_128kb": "0xb6a803cf", "region": "NTSC-U", "release_name": "Nordic Power Action Cartridge (USA, Europe) (v7.2) (Program)", "title": "Nordic Power Action Cartridge (USA, Europe) (v7.2)"}, "b8d0b9ce": {"crc32": "0xb8d0b9ce", "crc32_128kb": "0xe9591d93", "region": "PAL", "release_name": "Batman - The Movie (Europe)", "title": "Batman - The Movie"}, "b8f2b3b4": {"crc32": "0xb8f2b3b4", "crc32_128kb": "0xb8f2b3b4", "region": "NTSC-U", "release_name": "Action Cartridge Plus (Germany) (v6.0) (Program)", "title": "Action Cartridge Plus (Germany) (v6.0)"}, "b96f2c80": {"crc32": "0xb96f2c80", "crc32_128kb": "0xb96f2c80", "region": "NTSC-U", "release_name": "Final Cartridge III, The (USA, Europe) (Nov 87) (Program)", "title": "Final Cartridge III, The (USA, Europe) (Nov 87)"}, "b9a144e7": {"crc32": "0xb9a144e7", "crc32_128kb": "0xb9a144e7", "region": "NTSC-U", "release_name": "Rechenlowe, Der - Fit in Multiplikation und Division - 3.-4. Schuljahr (Germany)", "title": "Rechenlowe, Der - Fit in Multiplikation und Division - 3.-4. Schuljahr (Germany)"}, "b9d0df9c": {"crc32": "0xb9d0df9c", "crc32_128kb": "0x3b1a4d5b", "region": "PAL", "release_name": "Pang (Europe)", "title": "Pang"}, "b9f74014": {"crc32": "0xb9f74014", "crc32_128kb": "0xb9f74014", "region": "NTSC-U", "release_name": "Power Cartridge (USA, Europe) (Program)", "title": "Power Cartridge (USA, Europe)"}, "bb1685ce": {"crc32": "0xbb1685ce", "crc32_128kb": "0xbb1685ce", "region": "NTSC-U", "release_name": "Beamrider (USA, Europe)", "title": "Beamrider (USA, Europe)"}, "bb51284e": {"crc32": "0xbb51284e", "crc32_128kb": "0xbb51284e", "region": "NTSC-U", "release_name": "Kung-Fu Master (USA, Europe)", "title": "Kung-Fu Master (USA, Europe)"}, "bb587cc4": {"crc32": "0xbb587cc4", "crc32_128kb": "0xbb587cc4", "region": "NTSC-U", "release_name": "Videomate (USA, Europe) (Program)", "title": "Videomate (USA, Europe)"}, "bb9bd8b0": {"crc32": "0xbb9bd8b0", "crc32_128kb": "0xbb9bd8b0", "region": "NTSC-U", "release_name": "Mike Quarter (Present Sorter) (World) (Aftermarket) (Unl)", "title": "Mike Quarter (Present Sorter)"}, "bc06a876": {"crc32": "0xbc06a876", "crc32_128kb": "0xbc06a876", "region": "PAL", "release_name": "Action Replay Professional (Europe) (v3) (Program) (Unl)", "title": "Action Replay Professional (v3)"}, "be002f76": {"crc32": "0xbe002f76", "crc32_128kb": "0xbe002f76", "region": "NTSC-U", "release_name": "64 Doctor (USA, Europe) (Program)", "title": "64 Doctor (USA, Europe)"}, "bebcb664": {"crc32": "0xbebcb664", "crc32_128kb": "0xbebcb664", "region": "NTSC-U", "release_name": "Mr. TNT (USA, Europe)", "title": "Mr. TNT (USA, Europe)"}, "beceb54c": {"crc32": "0xbeceb54c", "crc32_128kb": "0x4258afca", "region": "PAL", "release_name": "Fiendish Freddy's Big Top o' Fun + International Soccer + Flimbo's Quest + Klax (Europe) (C 64 Games System)", "title": "Fiendish Freddy's Big Top o' Fun + International Soccer + Flimbo's Quest + Klax (C 64 Games System)"}, "bfa76444": {"crc32": "0xbfa76444", "crc32_128kb": "0xbfa76444", "region": "NTSC-U", "release_name": "Teledata (Sweden) (Program)", "title": "Teledata (Sweden)"}, "c0710a45": {"crc32": "0xc0710a45", "crc32_128kb": "0xc0710a45", "region": "NTSC-U", "release_name": "Oil's Well (USA, Europe)", "title": "Oil's Well (USA, Europe)"}, "c233227d": {"crc32": "0xc233227d", "crc32_128kb": "0xc233227d", "region": "NTSC-U", "release_name": "Black Box (USA, Europe) (v2.0) (Program)", "title": "Black Box (USA, Europe) (v2.0)"}, "c6b2cb39": {"crc32": "0xc6b2cb39", "crc32_128kb": "0xa7b95529", "region": "PAL", "release_name": "Toki (Europe)", "title": "Toki"}, "c741fa77": {"crc32": "0xc741fa77", "crc32_128kb": "0xc741fa77", "region": "NTSC-U", "release_name": "Magic Voice (USA, Europe) (Program)", "title": "Magic Voice (USA, Europe)"}, "c87f8844": {"crc32": "0xc87f8844", "crc32_128kb": "0xc87f8844", "region": "NTSC-U", "release_name": "Simons' BASIC (USA, Europe) (Program)", "title": "Simons' BASIC (USA, Europe)"}, "c99597c7": {"crc32": "0xc99597c7", "crc32_128kb": "0xc99597c7", "region": "NTSC-U", "release_name": "Omega Race (USA, Europe)", "title": "Omega Race (USA, Europe)"}, "cb06a7dd": {"crc32": "0xcb06a7dd", "crc32_128kb": "0xbdf89639", "region": "NTSC-U", "release_name": "Rechtschreiblowe, Der - Fit in Rechtschreibung - 3.-4. Schuljahr (Germany) (Teil 1)", "title": "Rechtschreiblowe, Der - Fit in Rechtschreibung - 3.-4. Schuljahr (Germany) (Teil 1)"}, "cb07fca6": {"crc32": "0xcb07fca6", "crc32_128kb": "0xcb07fca6", "region": "NTSC-U", "release_name": "Pancho (France)", "title": "Pancho (France)"}, "cb2cd61b": {"crc32": "0xcb2cd61b", "crc32_128kb": "0xcb2cd61b", "region": "NTSC-U", "release_name": "Frogger II - Threeedeep! (USA, Europe)", "title": "Frogger II - Threeedeep! (USA, Europe)"}, "cc72fd59": {"crc32": "0xcc72fd59", "crc32_128kb": "0xcc72fd59", "region": "NTSC-U", "release_name": "Nova Blast (USA, Europe)", "title": "Nova Blast (USA, Europe)"}, "cc80b501": {"crc32": "0xcc80b501", "crc32_128kb": "0xcc80b501", "region": "NTSC-U", "release_name": "Final Cartridge III, The (USA, Europe) (Sep 87) (Program)", "title": "Final Cartridge III, The (USA, Europe) (Sep 87)"}, "cc8d2a02": {"crc32": "0xcc8d2a02", "crc32_128kb": "0xcc8d2a02", "region": "NTSC-U", "release_name": "Alien Sidestep (USA, Europe)", "title": "Alien Sidestep (USA, Europe)"}, "cd22f373": {"crc32": "0xcd22f373", "crc32_128kb": "0xcd22f373", "region": "NTSC-U", "release_name": "Alf in the Color Caves (USA, Europe)", "title": "Alf in the Color Caves (USA, Europe)"}, "cd2ca138": {"crc32": "0xcd2ca138", "crc32_128kb": "0xcd2ca138", "region": "NTSC-U", "release_name": "Viduzzles - Computerized Jigsaw Puzzles (USA, Europe)", "title": "Viduzzles - Computerized Jigsaw Puzzles (USA, Europe)"}, "ce04e0ce": {"crc32": "0xce04e0ce", "crc32_128kb": "0xce04e0ce", "region": "NTSC-U", "release_name": "Colossus Chess + Silicon Syborgs + International Football (USA, Europe) (Super Games)", "title": "Colossus Chess + Silicon Syborgs + International Football (USA, Europe) (Super Games)"}, "d0d81fba": {"crc32": "0xd0d81fba", "crc32_128kb": "0xd0d81fba", "region": "NTSC-U", "release_name": "Viking Raider (USA, Europe)", "title": "Viking Raider (USA, Europe)"}, "d1dcf786": {"crc32": "0xd1dcf786", "crc32_128kb": "0x25627e9f", "region": "NTSC-U", "release_name": "Satan (USA, Europe)", "title": "Satan (USA, Europe)"}, "d2324a36": {"crc32": "0xd2324a36", "crc32_128kb": "0xd2324a36", "region": "NTSC-U", "release_name": "Princess and the Frog (USA, Europe)", "title": "Princess and the Frog (USA, Europe)"}, "d2324cd5": {"crc32": "0xd2324cd5", "crc32_128kb": "0xd2324cd5", "region": "NTSC-U", "release_name": "Centipede (USA, Europe) (2)", "title": "Centipede (USA, Europe) (2)"}, "d3007491": {"crc32": "0xd3007491", "crc32_128kb": "0xd3007491", "region": "NTSC-U", "release_name": "Dot Gobbler (USA, Europe)", "title": "Dot Gobbler (USA, Europe)"}, "d3165c28": {"crc32": "0xd3165c28", "crc32_128kb": "0xd3165c28", "region": "NTSC-U", "release_name": "Zaxxon (USA, Europe)", "title": "Zaxxon (USA, Europe)"}, "d536f2b6": {"crc32": "0xd536f2b6", "crc32_128kb": "0xd536f2b6", "region": "NTSC-U", "release_name": "Galaxions + Munchman (USA, Europe)", "title": "Galaxions + Munchman (USA, Europe)"}, "d53e8bda": {"crc32": "0xd53e8bda", "crc32_128kb": "0xd53e8bda", "region": "NTSC-U", "release_name": "Facemaker (USA, Europe)", "title": "Facemaker (USA, Europe)"}, "d550f094": {"crc32": "0xd550f094", "crc32_128kb": "0xd550f094", "region": "NTSC-U", "release_name": "64MON (USA, Europe) (v1.03) (Program)", "title": "64MON (USA, Europe) (v1.03)"}, "d5a4bbd6": {"crc32": "0xd5a4bbd6", "crc32_128kb": "0xd5a4bbd6", "region": "NTSC-U", "release_name": "Gyruss (USA, Europe)", "title": "Gyruss (USA, Europe)"}, "d6f59e50": {"crc32": "0xd6f59e50", "crc32_128kb": "0xd6f59e50", "region": "NTSC-U", "release_name": "Sales Cartridge (USA, Europe)", "title": "Sales Cartridge (USA, Europe)"}, "d73ce936": {"crc32": "0xd73ce936", "crc32_128kb": "0xd73ce936", "region": "NTSC-U", "release_name": "Bubble Burst (USA, Europe)", "title": "Bubble Burst (USA, Europe)"}, "d763bd3e": {"crc32": "0xd763bd3e", "crc32_128kb": "0xd763bd3e", "region": "NTSC-U", "release_name": "Lunar Leeper (USA, Europe)", "title": "Lunar Leeper (USA, Europe)"}, "d7c23075": {"crc32": "0xd7c23075", "crc32_128kb": "0xd7c23075", "region": "NTSC-U", "release_name": "Maze Man (USA, Europe)", "title": "Maze Man (USA, Europe)"}, "d7d2b1d1": {"crc32": "0xd7d2b1d1", "crc32_128kb": "0xd7d2b1d1", "region": "NTSC-U", "release_name": "Jungle Hunt (USA, Europe)", "title": "Jungle Hunt (USA, Europe)"}, "d853ad81": {"crc32": "0xd853ad81", "crc32_128kb": "0xd853ad81", "region": "NTSC-U", "release_name": "Robotron - 2084 (USA, Europe)", "title": "Robotron - 2084 (USA, Europe)"}, "d86ce20c": {"crc32": "0xd86ce20c", "crc32_128kb": "0xd86ce20c", "region": "NTSC-U", "release_name": "Pitstop (USA, Europe)", "title": "Pitstop (USA, Europe)"}, "d8b4c487": {"crc32": "0xd8b4c487", "crc32_128kb": "0xd8b4c487", "region": "NTSC-U", "release_name": "Retro Ball (USA, Europe)", "title": "Retro Ball (USA, Europe)"}, "db7659bf": {"crc32": "0xdb7659bf", "crc32_128kb": "0x62e1ca22", "region": "NTSC-U", "release_name": "COMAL 80 (USA, Europe) (Program)", "title": "COMAL 80 (USA, Europe)"}, "dc43cf24": {"crc32": "0xdc43cf24", "crc32_128kb": "0xdc43cf24", "region": "NTSC-U", "release_name": "Motor Mania (USA, Europe)", "title": "Motor Mania (USA, Europe)"}, "dc6aa143": {"crc32": "0xdc6aa143", "crc32_128kb": "0xdc6aa143", "region": "NTSC-U", "release_name": "Mountain King (USA, Europe)", "title": "Mountain King (USA, Europe)"}, "dd6c545a": {"crc32": "0xdd6c545a", "crc32_128kb": "0xdd6c545a", "region": "NTSC-U", "release_name": "Pagefox (Finland) (Program) (u1)", "title": "Pagefox (Finland) (u1)"}, "def7ca41": {"crc32": "0xdef7ca41", "crc32_128kb": "0xdef7ca41", "region": "NTSC-J", "release_name": "MINI BASIC I (Japan) (MAX)", "title": "MINI BASIC I (MAX)"}, "df734252": {"crc32": "0xdf734252", "crc32_128kb": "0x41b0702d", "region": "NTSC-U", "release_name": "Expert, The (USA, Europe) (Program) (Expert29)", "title": "Expert, The (USA, Europe) (Expert29)"}, "e07b8e79": {"crc32": "0xe07b8e79", "crc32_128kb": "0xe07b8e79", "region": "NTSC-U", "release_name": "Up & Add'Em (USA, Europe)", "title": "Up & Add'Em (USA, Europe)"}, "e25e76fe": {"crc32": "0xe25e76fe", "crc32_128kb": "0xe25e76fe", "region": "NTSC-U", "release_name": "C-64 Diagnostic (USA, Europe) (Rev 586220) (Program)", "title": "C-64 Diagnostic (USA, Europe) (Rev 586220)"}, "e2729a5c": {"crc32": "0xe2729a5c", "crc32_128kb": "0xe2729a5c", "region": "NTSC-U", "release_name": "Bridge 64 (USA, Europe)", "title": "Bridge 64 (USA, Europe)"}, "e2b01a12": {"crc32": "0xe2b01a12", "crc32_128kb": "0xe2b01a12", "region": "NTSC-U", "release_name": "COMAL 80 (USA, Europe) (Program)", "title": "COMAL 80 (USA, Europe)"}, "e370ed4e": {"crc32": "0xe370ed4e", "crc32_128kb": "0xe370ed4e", "region": "NTSC-U", "release_name": "Tenpins + Meteor Runner + Vortex (USA, Europe) (Megafun)", "title": "Tenpins + Meteor Runner + Vortex (USA, Europe) (Megafun)"}, "e3a92d06": {"crc32": "0xe3a92d06", "crc32_128kb": "0xe3a92d06", "region": "NTSC-U", "release_name": "Galaxian (USA, Europe)", "title": "Galaxian (USA, Europe)"}, "e49c6a5b": {"crc32": "0xe49c6a5b", "crc32_128kb": "0x78df5105", "region": "NTSC-U", "release_name": "Expert, The (USA, Europe) (Program) (Expert27)", "title": "Expert, The (USA, Europe) (Expert27)"}, "e4f6e636": {"crc32": "0xe4f6e636", "crc32_128kb": "0xe4f6e636", "region": "NTSC-U", "release_name": "Defender (USA, Europe)", "title": "Defender (USA, Europe)"}, "e5b26a61": {"crc32": "0xe5b26a61", "crc32_128kb": "0xe5b26a61", "region": "NTSC-U", "release_name": "Activision Decathlon, The (USA, Europe)", "title": "Activision Decathlon, The (USA, Europe)"}, "e5d52591": {"crc32": "0xe5d52591", "crc32_128kb": "0xe5d52591", "region": "NTSC-U", "release_name": "C64-FORTH (USA, Europe) (Program)", "title": "C64-FORTH (USA, Europe)"}, "e70444c6": {"crc32": "0xe70444c6", "crc32_128kb": "0xe70444c6", "region": "NTSC-U", "release_name": "Pitfall II - Lost Caverns (USA, Europe)", "title": "Pitfall II - Lost Caverns (USA, Europe)"}, "e7811620": {"crc32": "0xe7811620", "crc32_128kb": "0xe7811620", "region": "NTSC-U", "release_name": "LeMans (USA, Europe) (MAX)", "title": "LeMans (USA, Europe) (MAX)"}, "e7882b07": {"crc32": "0xe7882b07", "crc32_128kb": "0xe7882b07", "region": "NTSC-J", "release_name": "Wizard of Wor (Japan) (v02) (MAX)", "title": "Wizard of Wor (v02) (MAX)"}, "e894e448": {"crc32": "0xe894e448", "crc32_128kb": "0xe894e448", "region": "NTSC-U", "release_name": "IEEE-488 (USA, Europe) (Program)", "title": "IEEE-488 (USA, Europe)"}, "e9066e6c": {"crc32": "0xe9066e6c", "crc32_128kb": "0xe9066e6c", "region": "NTSC-U", "release_name": "Buck Rogers - Planet of Zoom (USA, Europe)", "title": "Buck Rogers - Planet of Zoom (USA, Europe)"}, "eb462b4a": {"crc32": "0xeb462b4a", "crc32_128kb": "0xeb462b4a", "region": "NTSC-U", "release_name": "Lazer Zone (USA, Europe)", "title": "Lazer Zone (USA, Europe)"}, "eb4abb78": {"crc32": "0xeb4abb78", "crc32_128kb": "0xeb4abb78", "region": "NTSC-U", "release_name": "Save New York (USA, Europe)", "title": "Save New York (USA, Europe)"}, "eb5171ae": {"crc32": "0xeb5171ae", "crc32_128kb": "0xeb5171ae", "region": "NTSC-U", "release_name": "Conrad Disk Booster (Germany) (Program)", "title": "Conrad Disk Booster (Germany)"}, "ed0c9c7d": {"crc32": "0xed0c9c7d", "crc32_128kb": "0xed0c9c7d", "region": "NTSC-U", "release_name": "REX-Ramfloppy (USA, Europe) (v4.0) (Program)", "title": "REX-Ramfloppy (USA, Europe) (v4.0)"}, "ed637539": {"crc32": "0xed637539", "crc32_128kb": "0xed637539", "region": "NTSC-U", "release_name": "Castle Hassle (USA, Europe)", "title": "Castle Hassle (USA, Europe)"}, "ed84c27b": {"crc32": "0xed84c27b", "crc32_128kb": "0xf389b689", "region": "NTSC-U", "release_name": "Calc Result - The Spread Sheet - Advanced (USA, Europe) (Program)", "title": "Calc Result - The Spread Sheet - Advanced (USA, Europe)"}, "ee3e2cd7": {"crc32": "0xee3e2cd7", "crc32_128kb": "0x28de7439", "region": "NTSC-U", "release_name": "Double Dragon (USA, Europe) (Ocean)", "title": "Double Dragon (USA, Europe) (Ocean)"}, "eea2850e": {"crc32": "0xeea2850e", "crc32_128kb": "0x4c399ffe", "region": "NTSC-U", "release_name": "Counterweight Kate (World) (Aftermarket) (Unl)", "title": "Counterweight Kate"}, "ef886e9c": {"crc32": "0xef886e9c", "crc32_128kb": "0xcc9501a2", "region": "NTSC-U", "release_name": "Pacman (World) (Aftermarket) (Unl)", "title": "Pacman"}, "efb293d1": {"crc32": "0xefb293d1", "crc32_128kb": "0xefb293d1", "region": "NTSC-U", "release_name": "Big Bird's Special Delivery (USA, Europe)", "title": "Big Bird's Special Delivery (USA, Europe)"}, "efb363e9": {"crc32": "0xefb363e9", "crc32_128kb": "0xefb363e9", "region": "NTSC-U", "release_name": "Dig Dug (USA, Europe)", "title": "Dig Dug (USA, Europe)"}, "f03b154d": {"crc32": "0xf03b154d", "crc32_128kb": "0xf03b154d", "region": "NTSC-U", "release_name": "Trashman (USA, Europe)", "title": "Trashman (USA, Europe)"}, "f10447a9": {"crc32": "0xf10447a9", "crc32_128kb": "0xf10447a9", "region": "NTSC-U", "release_name": "Astroblitz (USA, Europe)", "title": "Astroblitz (USA, Europe)"}, "f3489d8f": {"crc32": "0xf3489d8f", "crc32_128kb": "0x80ec4c96", "region": "NTSC-U", "release_name": "Viking Raider (USA, Europe)", "title": "Viking Raider (USA, Europe)"}, "f3819376": {"crc32": "0xf3819376", "crc32_128kb": "0xf3819376", "region": "NTSC-U", "release_name": "Crystal Castles (USA, Europe) (Proto)", "title": "Crystal Castles (USA, Europe)"}, "f4267ab7": {"crc32": "0xf4267ab7", "crc32_128kb": "0xf4267ab7", "region": "NTSC-U", "release_name": "Froop (World) (Aftermarket) (Unl)", "title": "Froop"}, "f48f6b0f": {"crc32": "0xf48f6b0f", "crc32_128kb": "0xf48f6b0f", "region": "NTSC-U", "release_name": "Frog Master (USA, Europe)", "title": "Frog Master (USA, Europe)"}, "f569c49c": {"crc32": "0xf569c49c", "crc32_128kb": "0xf569c49c", "region": "NTSC-U", "release_name": "Calc Result - The Spread Sheet - Easy (USA, Europe) (Program) (ECRGRN)", "title": "Calc Result - The Spread Sheet - Easy (USA, Europe) (ECRGRN)"}, "f617bec4": {"crc32": "0xf617bec4", "crc32_128kb": "0xf617bec4", "region": "NTSC-U", "release_name": "Calc Result - The Spread Sheet - Easy (USA, Europe) (Program) (Alt) (hn61364)", "title": "Calc Result - The Spread Sheet - Easy (USA, Europe) (hn61364)"}, "f61edcfe": {"crc32": "0xf61edcfe", "crc32_128kb": "0xf61edcfe", "region": "NTSC-U", "release_name": "ExBASIC Level II (USA, Europe) (v64.1) (Program)", "title": "ExBASIC Level II (USA, Europe) (v64.1)"}, "f6986145": {"crc32": "0xf6986145", "crc32_128kb": "0xf6986145", "region": "NTSC-U", "release_name": "Final Cartridge III, The (USA, Europe) (May 88) (Program)", "title": "Final Cartridge III, The (USA, Europe) (May 88)"}, "f71185e8": {"crc32": "0xf71185e8", "crc32_128kb": "0xf71185e8", "region": "NTSC-U", "release_name": "James Bond 007 (USA, Europe)", "title": "James Bond 007 (USA, Europe)"}, "f8b67adc": {"crc32": "0xf8b67adc", "crc32_128kb": "0xf8b67adc", "region": "NTSC-J", "release_name": "Road Race (Japan) (v02) (MAX)", "title": "Road Race (v02) (MAX)"}, "f8d2cf86": {"crc32": "0xf8d2cf86", "crc32_128kb": "0xf8d2cf86", "region": "NTSC-U", "release_name": "Taz (World) (Aftermarket) (Unl)", "title": "Taz"}, "f9cfacfd": {"crc32": "0xf9cfacfd", "crc32_128kb": "0xf9cfacfd", "region": "NTSC-U", "release_name": "Star Post (USA, Europe)", "title": "Star Post (USA, Europe)"}, "fa224abf": {"crc32": "0xfa224abf", "crc32_128kb": "0xfa224abf", "region": "NTSC-J", "release_name": "Wizard of Wor (Japan) (MAX)", "title": "Wizard of Wor (MAX)"}, "fb321df1": {"crc32": "0xfb321df1", "crc32_128kb": "0xfb321df1", "region": "NTSC-U", "release_name": "Frogger + River Raid + Activision Decathlon, The + Beamrider (USA, Europe) (Arcade Classic Pak)", "title": "Frogger + River Raid + Activision Decathlon, The + Beamrider (USA, Europe) (Arcade Classic Pak)"}, "fb55c641": {"crc32": "0xfb55c641", "crc32_128kb": "0xfb55c641", "region": "NTSC-U", "release_name": "Visible Solar System, The (USA, Europe) (MAX)", "title": "Visible Solar System, The (USA, Europe) (MAX)"}, "fc50720e": {"crc32": "0xfc50720e", "crc32_128kb": "0xfc50720e", "region": "NTSC-U", "release_name": "Alpha Build (USA, Europe)", "title": "Alpha Build (USA, Europe)"}, "fc6383a8": {"crc32": "0xfc6383a8", "crc32_128kb": "0xfc6383a8", "region": "NTSC-U", "release_name": "Super Sketch (USA, Europe)", "title": "Super Sketch (USA, Europe)"}, "fd200a52": {"crc32": "0xfd200a52", "crc32_128kb": "0xfd200a52", "region": "NTSC-U", "release_name": "Spitball (USA, Europe)", "title": "Spitball (USA, Europe)"}, "fde73767": {"crc32": "0xfde73767", "crc32_128kb": "0xfde73767", "region": "NTSC-U", "release_name": "Magic Desk I - Type and File (USA, Europe) (CCS) (Program)", "title": "Magic Desk I - Type and File (USA, Europe) (CCS)"}, "fe7e501c": {"crc32": "0xfe7e501c", "crc32_128kb": "0xfe7e501c", "region": "NTSC-U", "release_name": "Memory Manor (USA, Europe)", "title": "Memory Manor (USA, Europe)"}, "ff750341": {"crc32": "0xff750341", "crc32_128kb": "0xb58092fa", "region": "PAL", "release_name": "RoboCop 2 (Europe)", "title": "RoboCop 2"}, "ffb40ae8": {"crc32": "0xffb40ae8", "crc32_128kb": "0xffb40ae8", "region": "NTSC-U", "release_name": "VIC-Text 64 (Sweden) (Program)", "title": "VIC-Text 64 (Sweden)"}, "ffcb7904": {"crc32": "0xffcb7904", "crc32_128kb": "0xffcb7904", "region": "NTSC-U", "release_name": "Q-bert (USA, Europe)", "title": "Q-bert (USA, Europe)"}, "fff97d02": {"crc32": "0xfff97d02", "crc32_128kb": "0xfff97d02", "region": "NTSC-U", "release_name": "Pinball Spectacular (World) (MAX)", "title": "Pinball Spectacular (MAX)"}}